simple_connect/__init__.py
simple_connect/connect.py
simple_connect-1.1.0.dist-info/LICENSE
simple_connect-1.1.0.dist-info/METADATA
simple_connect-1.1.0.dist-info/WHEEL
simple_connect-1.1.0.dist-info/top_level.txt
simple_connect-1.1.0.dist-info/RECORD
