Metadata-Version: 2.1
Name: simple-connect
Version: 1.1.0
Summary: Simplify SQL Connection for data analysis
Home-page: https://github.com/saeed-abdul-rahim/simple_connect
Author: Saeed
Author-email: Saeed Abdul Rahim <sae.ar2@gmail.com>
Project-URL: Homepage, https://github.com/saeed-abdul-rahim/simple_connect
Project-URL: Bug Tracker, https://github.com/saeed-abdul-rahim/simple_connect/issues
Classifier: Programming Language :: Python :: 3
Classifier: License :: OSI Approved :: MIT License
Classifier: Operating System :: OS Independent
Requires-Python: >=3.7
License-File: LICENSE
Requires-Dist: httplib2
Requires-Dist: oauth2client
Requires-Dist: pandas
Requires-Dist: pymysql
Requires-Dist: sqlalchemy
Requires-Dist: sshtunnel
Requires-Dist: google-api-python-client
Requires-Dist: boto3
Requires-Dist: tqdm
Requires-Dist: paramiko
